Gfruit/__init__.py
Gfruit/browser_use.py
Gfruit/db_manager.py
gfruit-0.1.1.dist-info/licenses/LICENSE
gfruit-0.1.1.dist-info/METADATA
gfruit-0.1.1.dist-info/WHEEL
gfruit-0.1.1.dist-info/top_level.txt
gfruit-0.1.1.dist-info/RECORD
