Metadata-Version: 2.4
Name: Gfruit
Version: 0.1.1
Summary: A package for browser automation and database management
Author-email: Your Name <your.email@example.com>
License-Expression: MIT
Project-URL: Homepage, https://github.com/yourusername/Gfruit
Project-URL: Bug Tracker, https://github.com/yourusername/Gfruit/issues
Classifier: Development Status :: 3 - Alpha
Classifier: Intended Audience :: Developers
Classifier: Operating System :: OS Independent
Classifier: Programming Language :: Python :: 3
Classifier: Programming Language :: Python :: 3.7
Classifier: Programming Language :: Python :: 3.8
Classifier: Programming Language :: Python :: 3.9
Classifier: Programming Language :: Python :: 3.10
Classifier: Programming Language :: Python :: 3.11
Requires-Python: >=3.7
License-File: LICENSE
Requires-Dist: keyboard~=0.13.5
Requires-Dist: requests~=2.32.4
Requires-Dist: psutil~=7.0.0
Requires-Dist: selenium~=4.34.2
Requires-Dist: loguru~=0.7.3
Requires-Dist: web3~=7.12.1
Requires-Dist: webdriver-manager~=4.0.2
Requires-Dist: PyMySQL~=1.1.1
Dynamic: license-file
